asposewordscloud/__init__.py
asposewordscloud/api_client.py
asposewordscloud/configuration.py
asposewordscloud/rest.py
asposewordscloud/apis/__init__.py
asposewordscloud/apis/words_api.py
asposewordscloud/models/__init__.py
asposewordscloud/models/aspose_response.py
asposewordscloud/models/available_fonts_response.py
asposewordscloud/models/bmp_save_options_data.py
asposewordscloud/models/bookmark.py
asposewordscloud/models/bookmark_data.py
asposewordscloud/models/bookmark_response.py
asposewordscloud/models/bookmarks.py
asposewordscloud/models/bookmarks_outline_level_data.py
asposewordscloud/models/bookmarks_response.py
asposewordscloud/models/border.py
asposewordscloud/models/border_response.py
asposewordscloud/models/borders_collection.py
asposewordscloud/models/borders_response.py
asposewordscloud/models/classification_response.py
asposewordscloud/models/classification_result.py
asposewordscloud/models/comment.py
asposewordscloud/models/comment_link.py
asposewordscloud/models/comment_response.py
asposewordscloud/models/comments_collection.py
asposewordscloud/models/comments_response.py
asposewordscloud/models/compare_data.py
asposewordscloud/models/doc_save_options_data.py
asposewordscloud/models/document.py
asposewordscloud/models/document_entry.py
asposewordscloud/models/document_entry_list.py
asposewordscloud/models/document_position.py
asposewordscloud/models/document_properties.py
asposewordscloud/models/document_properties_response.py
asposewordscloud/models/document_property.py
asposewordscloud/models/document_property_response.py
asposewordscloud/models/document_response.py
asposewordscloud/models/document_stat_data.py
asposewordscloud/models/downsample_options_data.py
asposewordscloud/models/drawing_object.py
asposewordscloud/models/drawing_object_collection.py
asposewordscloud/models/drawing_object_link.py
asposewordscloud/models/drawing_object_response.py
asposewordscloud/models/drawing_objects_response.py
asposewordscloud-18.9.0.dist-info/LICENSE
asposewordscloud-18.9.0.dist-info/METADATA
asposewordscloud-18.9.0.dist-info/WHEEL
asposewordscloud-18.9.0.dist-info/top_level.txt
asposewordscloud-18.9.0.dist-info/RECORD
