Metadata-Version: 2.1
Name: asposewordscloud
Version: 18.9.0
Summary: Aspose.Words for Cloud API Reference
Home-page: https://github.com/aspose-words-cloud
Author: Yaroslaw Ekimov
Author-email: yaroslaw.ekimov@aspose.com
License: UNKNOWN
Keywords: aspose,python,aspose cloud,word
Platform: UNKNOWN
Classifier: Development Status :: 5 - Production/Stable
Classifier: Intended Audience :: Developers
Classifier: Topic :: Office/Business :: Office Suites
Classifier: Topic :: Software Development :: Libraries
Classifier: License :: OSI Approved :: MIT License
Classifier: Programming Language :: Python :: 2.7
Classifier: Programming Language :: Python :: 3.4
Classifier: Programming Language :: Python :: 3.5
Classifier: Programming Language :: Python :: 3.6
Requires-Dist: urllib3 (>=1.15)
Requires-Dist: six (>=1.10)
Requires-Dist: certifi
Requires-Dist: python-dateutil
